mbd_core/__init__.py
mbd_core/data/__init__.py
mbd_core/data/languages.py
mbd_core/data/schema.py
mbd_core/data/farcaster/__init__.py
mbd_core/data/farcaster/transform_functions.py
mbd_core/data/farcaster/utils.py
mbd_core/enrich/__init__.py
mbd_core/enrich/schema.py
mbd_core/enrich/labelling/__init__.py
mbd_core/enrich/labelling/config.json
mbd_core/enrich/labelling/load_config.py
mbd_core/zora/__init__.py
mbd_core/zora/schema.py
mbd_core/zora/zora_api.py
mbd_core-4.0.0.dist-info/METADATA
mbd_core-4.0.0.dist-info/WHEEL
mbd_core-4.0.0.dist-info/top_level.txt
mbd_core-4.0.0.dist-info/RECORD
