Metadata-Version: 2.4
Name: mbd_core
Version: 4.0.0
Summary: Common definitions for mbd recommender system.
Home-page: https://mbd.xyz
Author: mbd ds team
Author-email: na@mbd.xyz
License: MIT
Requires-Python: ~=3.10
Requires-Dist: pydantic
Requires-Dist: pydantic-settings
Requires-Dist: pandas
Requires-Dist: pandera
Requires-Dist: fasttext-langdetect
Requires-Dist: emoji
Requires-Dist: aiohttp
Requires-Dist: pyarrow
Requires-Dist: types-requests
Requires-Dist: black
Requires-Dist: twine
Dynamic: author
Dynamic: author-email
Dynamic: description
Dynamic: description-content-type
Dynamic: home-page
Dynamic: license
Dynamic: requires-dist
Dynamic: requires-python
Dynamic: summary
